twpm/__init__.py
twpm/core/__init__.py
twpm/core/chain.py
twpm/core/container.py
twpm/core/cursor.py
twpm/core/decorators.py
twpm/core/depedencies.py
twpm/core/orchestrator.py
twpm/core/base/__init__.py
twpm/core/base/enums.py
twpm/core/base/models.py
twpm/core/base/node.py
twpm/core/base/types.py
twpm/core/primitives/__init__.py
twpm/core/primitives/condition.py
twpm/core/primitives/task.py
twpm/dsa/__init__.py
twpm/dsa/doublelinkedlist.py
twpm/dsa/linkedlist.py
twpm-0.1.1.dist-info/METADATA
twpm-0.1.1.dist-info/WHEEL
twpm-0.1.1.dist-info/licenses/LICENSE
twpm-0.1.1.dist-info/RECORD
